pdf_table_generator/__init__.py
pdf_table_generator/generator.py
pdf_table_generator-0.1.0.dist-info/METADATA
pdf_table_generator-0.1.0.dist-info/WHEEL
pdf_table_generator-0.1.0.dist-info/top_level.txt
pdf_table_generator-0.1.0.dist-info/RECORD
