Metadata-Version: 2.4
Name: pdf_table_generator
Version: 0.1.0
Summary: Generate PDF tables with dynamic headers, wrapping, and styling using fpdf
Author: RAJASEKAR E C <rajasekar_e_c@outlook.com>
Requires-Python: >=3.7
Requires-Dist: fpdf
Dynamic: author
Dynamic: requires-dist
Dynamic: requires-python
Dynamic: summary
